glacier_flow_model/__init__.py
glacier_flow_model/data/__init__.py
glacier_flow_model/data/access.py
glacier_flow_model/data/aletsch.tif
glacier_flow_model/fracd8/__init__.py
glacier_flow_model/fracd8/direction.py
glacier_flow_model/fracd8/flow.py
glacier_flow_model/fracd8/infinite.py
glacier_flow_model/fracd8/limited.py
glacier_flow_model/model.py
glacier_flow_model/utils/__init__.py
glacier_flow_model/utils/hillshade.py
glacier_flow_model/utils/store.py
glacier_flow_model-0.4.0.dist-info/LICENSE
glacier_flow_model-0.4.0.dist-info/METADATA
glacier_flow_model-0.4.0.dist-info/WHEEL
glacier_flow_model-0.4.0.dist-info/RECORD
