Metadata-Version: 2.1
Name: glacier-flow-model
Version: 0.4.0
Summary: Modeling glaciers on a digital elevation model based on mass balance and a modified D8 flow algorithm applied to ice
Home-page: https://pypi.org/project/glacier-flow-model/
License: MIT
Author: Merlin Unterfinger
Author-email: info@munterfinger.ch
Maintainer: Merlin Unterfinger
Maintainer-email: info@munterfinger.ch
Requires-Python: >=3.11,<4.0
Classifier: License :: OSI Approved :: MIT License
Classifier: Programming Language :: Python :: 3
Classifier: Programming Language :: Python :: 3.11
Classifier: Programming Language :: Python :: 3.12
Requires-Dist: matplotlib (>=3.8.2,<4.0.0)
Requires-Dist: numba (>=0.58.1,<0.59.0)
Requires-Dist: numpy (>=1.26.2,<2.0.0)
Requires-Dist: rasterio (>=1.3.9,<2.0.0)
Requires-Dist: scipy (>=1.11.4,<2.0.0)
Project-URL: Documentation, https://glacier-flow-model.readthedocs.io/en/latest/
Project-URL: Repository, https://github.com/munterfi/glacier-flow-model
